Metadata-Version: 2.1
Name: pygamepad
Version: 0.2
Summary: A module that allows you to control your gamepad
Home-page: http://github.com/tinytengu/pygamepad
Author: tinytengu
Author-email: tinytengu@yandex.ru
License: GPT-3
Platform: UNKNOWN
License-File: LICENSE
